{"nodes": [{"id": "services_crypton_demo_src_appshell_js", "label": "AppShell.js", "file_type": "code", "source_file": "services\\crypton-demo\\src\\AppShell.js", "source_location": "L1"}, {"id": "appshell_breadcrumb", "label": "Breadcrumb()", "file_type": "code", "source_file": "services\\crypton-demo\\src\\AppShell.js", "source_location": "L7"}, {"id": "appshell_sidebar", "label": "Sidebar()", "file_type": "code", "source_file": "services\\crypton-demo\\src\\AppShell.js", "source_location": "L18"}, {"id": "appshell_mobileheader", "label": "MobileHeader()", "file_type": "code", "source_file": "services\\crypton-demo\\src\\AppShell.js", "source_location": "L117"}, {"id": "appshell_appshell", "label": "AppShell()", "file_type": "code", "source_file": "services\\crypton-demo\\src\\AppShell.js", "source_location": "L126"}], "edges": [{"source": "services_crypton_demo_src_appshell_js", "target": "react", "relation": "imports_from", "confidence": "EXTRACTED", "source_file": "services\\crypton-demo\\src\\AppShell.js", "source_location": "L1", "weight": 1.0}, {"source": "services_crypton_demo_src_appshell_js", "target": "services_crypton_demo_src_constants", "relation": "imports_from", "confidence": "EXTRACTED", "source_file": "services\\crypton-demo\\src\\AppShell.js", "source_location": "L2", "weight": 1.0}, {"source": "services_crypton_demo_src_appshell_js", "target": "services_crypton_demo_src_authcontext", "relation": "imports_from", "confidence": "EXTRACTED", "source_file": "services\\crypton-demo\\src\\AppShell.js", "source_location": "L3", "weight": 1.0}, {"source": "services_crypton_demo_src_appshell_js", "target": "services_crypton_demo_src_auth", "relation": "imports_from", "confidence": "EXTRACTED", "source_file": "services\\crypton-demo\\src\\AppShell.js", "source_location": "L4", "weight": 1.0}, {"source": "services_crypton_demo_src_appshell_js", "target": "services_crypton_demo_src_config", "relation": "imports_from", "confidence": "EXTRACTED", "source_file": "services\\crypton-demo\\src\\AppShell.js", "source_location": "L5", "weight": 1.0}, {"source": "services_crypton_demo_src_appshell_js", "target": "appshell_breadcrumb", "relation": "contains", "confidence": "EXTRACTED", "source_file": "services\\crypton-demo\\src\\AppShell.js", "source_location": "L7", "weight": 1.0}, {"source": "services_crypton_demo_src_appshell_js", "target": "appshell_sidebar", "relation": "contains", "confidence": "EXTRACTED", "source_file": "services\\crypton-demo\\src\\AppShell.js", "source_location": "L18", "weight": 1.0}, {"source": "services_crypton_demo_src_appshell_js", "target": "appshell_mobileheader", "relation": "contains", "confidence": "EXTRACTED", "source_file": "services\\crypton-demo\\src\\AppShell.js", "source_location": "L117", "weight": 1.0}, {"source": "services_crypton_demo_src_appshell_js", "target": "appshell_appshell", "relation": "contains", "confidence": "EXTRACTED", "source_file": "services\\crypton-demo\\src\\AppShell.js", "source_location": "L126", "weight": 1.0}], "raw_calls": [{"caller_nid": "appshell_sidebar", "callee": "useAuth", "source_file": "services\\crypton-demo\\src\\AppShell.js", "source_location": "L19"}, {"caller_nid": "appshell_sidebar", "callee": "has", "source_file": "services\\crypton-demo\\src\\AppShell.js", "source_location": "L20"}, {"caller_nid": "appshell_sidebar", "callee": "sectionLabel", "source_file": "services\\crypton-demo\\src\\AppShell.js", "source_location": "L80"}, {"caller_nid": "appshell_sidebar", "callee": "map", "source_file": "services\\crypton-demo\\src\\AppShell.js", "source_location": "L81"}, {"caller_nid": "appshell_sidebar", "callee": "sectionLabel", "source_file": "services\\crypton-demo\\src\\AppShell.js", "source_location": "L92"}, {"caller_nid": "appshell_sidebar", "callee": "map", "source_file": "services\\crypton-demo\\src\\AppShell.js", "source_location": "L93"}, {"caller_nid": "appshell_appshell", "callee": "useState", "source_file": "services\\crypton-demo\\src\\AppShell.js", "source_location": "L127"}]}