{"nodes": [{"id": "services_crypton_demo_src_app_js", "label": "App.js", "file_type": "code", "source_file": "services\\crypton-demo\\src\\App.js", "source_location": "L1"}, {"id": "app_canrenderlocalauthui", "label": "canRenderLocalAuthUi()", "file_type": "code", "source_file": "services\\crypton-demo\\src\\App.js", "source_location": "L44"}, {"id": "app_redirecttoauthui", "label": "redirectToAuthUi()", "file_type": "code", "source_file": "services\\crypton-demo\\src\\App.js", "source_location": "L50"}, {"id": "app_fontlink", "label": "FontLink()", "file_type": "code", "source_file": "services\\crypton-demo\\src\\App.js", "source_location": "L62"}, {"id": "app_toaststack", "label": "ToastStack()", "file_type": "code", "source_file": "services\\crypton-demo\\src\\App.js", "source_location": "L83"}, {"id": "app_pageloadskeleton", "label": "PageLoadSkeleton()", "file_type": "code", "source_file": "services\\crypton-demo\\src\\App.js", "source_location": "L114"}, {"id": "app_app", "label": "App()", "file_type": "code", "source_file": "services\\crypton-demo\\src\\App.js", "source_location": "L145"}], "edges": [{"source": "services_crypton_demo_src_app_js", "target": "react", "relation": "imports_from", "confidence": "EXTRACTED", "source_file": "services\\crypton-demo\\src\\App.js", "source_location": "L1", "weight": 1.0}, {"source": "services_crypton_demo_src_app_js", "target": "services_crypton_demo_src_authcontext", "relation": "imports_from", "confidence": "EXTRACTED", "source_file": "services\\crypton-demo\\src\\App.js", "source_location": "L2", "weight": 1.0}, {"source": "services_crypton_demo_src_app_js", "target": "services_crypton_demo_src_panelwall", "relation": "imports_from", "confidence": "EXTRACTED", "source_file": "services\\crypton-demo\\src\\App.js", "source_location": "L3", "weight": 1.0}, {"source": "services_crypton_demo_src_app_js", "target": "services_crypton_demo_src_auth", "relation": "imports_from", "confidence": "EXTRACTED", "source_file": "services\\crypton-demo\\src\\App.js", "source_location": "L4", "weight": 1.0}, {"source": "services_crypton_demo_src_app_js", "target": "services_crypton_demo_src_api", "relation": "imports_from", "confidence": "EXTRACTED", "source_file": "services\\crypton-demo\\src\\App.js", "source_location": "L5", "weight": 1.0}, {"source": "services_crypton_demo_src_app_js", "target": "services_crypton_demo_src_routes", "relation": "imports_from", "confidence": "EXTRACTED", "source_file": "services\\crypton-demo\\src\\App.js", "source_location": "L6", "weight": 1.0}, {"source": "services_crypton_demo_src_app_js", "target": "services_crypton_demo_src_constants", "relation": "imports_from", "confidence": "EXTRACTED", "source_file": "services\\crypton-demo\\src\\App.js", "source_location": "L7", "weight": 1.0}, {"source": "services_crypton_demo_src_app_js", "target": "services_crypton_demo_src_appshell", "relation": "imports_from", "confidence": "EXTRACTED", "source_file": "services\\crypton-demo\\src\\App.js", "source_location": "L8", "weight": 1.0}, {"source": "services_crypton_demo_src_app_js", "target": "services_crypton_demo_src_buttons", "relation": "imports_from", "confidence": "EXTRACTED", "source_file": "services\\crypton-demo\\src\\App.js", "source_location": "L9", "weight": 1.0}, {"source": "services_crypton_demo_src_app_js", "target": "services_crypton_demo_src_hooks", "relation": "imports_from", "confidence": "EXTRACTED", "source_file": "services\\crypton-demo\\src\\App.js", "source_location": "L10", "weight": 1.0}, {"source": "services_crypton_demo_src_app_js", "target": "services_crypton_demo_src_landing", "relation": "imports_from", "confidence": "EXTRACTED", "source_file": "services\\crypton-demo\\src\\App.js", "source_location": "L12", "weight": 1.0}, {"source": "services_crypton_demo_src_app_js", "target": "services_crypton_demo_src_login", "relation": "imports_from", "confidence": "EXTRACTED", "source_file": "services\\crypton-demo\\src\\App.js", "source_location": "L13", "weight": 1.0}, {"source": "services_crypton_demo_src_app_js", "target": "services_crypton_demo_src_adminlogin", "relation": "imports_from", "confidence": "EXTRACTED", "source_file": "services\\crypton-demo\\src\\App.js", "source_location": "L14", "weight": 1.0}, {"source": "services_crypton_demo_src_app_js", "target": "services_crypton_demo_src_register", "relation": "imports_from", "confidence": "EXTRACTED", "source_file": "services\\crypton-demo\\src\\App.js", "source_location": "L15", "weight": 1.0}, {"source": "services_crypton_demo_src_app_js", "target": "services_crypton_demo_src_dashboard", "relation": "imports_from", "confidence": "EXTRACTED", "source_file": "services\\crypton-demo\\src\\App.js", "source_location": "L16", "weight": 1.0}, {"source": "services_crypton_demo_src_app_js", "target": "services_crypton_demo_src_devices", "relation": "imports_from", "confidence": "EXTRACTED", "source_file": "services\\crypton-demo\\src\\App.js", "source_location": "L17", "weight": 1.0}, {"source": "services_crypton_demo_src_app_js", "target": "services_crypton_demo_src_demo_app_demoactions", "relation": "imports_from", "confidence": "EXTRACTED", "source_file": "services\\crypton-demo\\src\\App.js", "source_location": "L18", "weight": 1.0}, {"source": "services_crypton_demo_src_app_js", "target": "services_crypton_demo_src_admin", "relation": "imports_from", "confidence": "EXTRACTED", "source_file": "services\\crypton-demo\\src\\App.js", "source_location": "L20", "weight": 1.0}, {"source": "services_crypton_demo_src_app_js", "target": "services_crypton_demo_src_admindashboard", "relation": "imports_from", "confidence": "EXTRACTED", "source_file": "services\\crypton-demo\\src\\App.js", "source_location": "L21", "weight": 1.0}, {"source": "services_crypton_demo_src_app_js", "target": "services_crypton_demo_src_auditlogs", "relation": "imports_from", "confidence": "EXTRACTED", "source_file": "services\\crypton-demo\\src\\App.js", "source_location": "L22", "weight": 1.0}, {"source": "services_crypton_demo_src_app_js", "target": "services_crypton_demo_src_sessions", "relation": "imports_from", "confidence": "EXTRACTED", "source_file": "services\\crypton-demo\\src\\App.js", "source_location": "L23", "weight": 1.0}, {"source": "services_crypton_demo_src_app_js", "target": "services_crypton_demo_src_recovery", "relation": "imports_from", "confidence": "EXTRACTED", "source_file": "services\\crypton-demo\\src\\App.js", "source_location": "L24", "weight": 1.0}, {"source": "services_crypton_demo_src_app_js", "target": "services_crypton_demo_src_rbac", "relation": "imports_from", "confidence": "EXTRACTED", "source_file": "services\\crypton-demo\\src\\App.js", "source_location": "L25", "weight": 1.0}, {"source": "services_crypton_demo_src_app_js", "target": "services_crypton_demo_src_policyengine", "relation": "imports_from", "confidence": "EXTRACTED", "source_file": "services\\crypton-demo\\src\\App.js", "source_location": "L26", "weight": 1.0}, {"source": "services_crypton_demo_src_app_js", "target": "services_crypton_demo_src_riskintel", "relation": "imports_from", "confidence": "EXTRACTED", "source_file": "services\\crypton-demo\\src\\App.js", "source_location": "L27", "weight": 1.0}, {"source": "services_crypton_demo_src_app_js", "target": "services_crypton_demo_src_orgsettings", "relation": "imports_from", "confidence": "EXTRACTED", "source_file": "services\\crypton-demo\\src\\App.js", "source_location": "L28", "weight": 1.0}, {"source": "services_crypton_demo_src_app_js", "target": "app_canrenderlocalauthui", "relation": "contains", "confidence": "EXTRACTED", "source_file": "services\\crypton-demo\\src\\App.js", "source_location": "L44", "weight": 1.0}, {"source": "services_crypton_demo_src_app_js", "target": "app_redirecttoauthui", "relation": "contains", "confidence": "EXTRACTED", "source_file": "services\\crypton-demo\\src\\App.js", "source_location": "L50", "weight": 1.0}, {"source": "services_crypton_demo_src_app_js", "target": "app_fontlink", "relation": "contains", "confidence": "EXTRACTED", "source_file": "services\\crypton-demo\\src\\App.js", "source_location": "L62", "weight": 1.0}, {"source": "services_crypton_demo_src_app_js", "target": "app_toaststack", "relation": "contains", "confidence": "EXTRACTED", "source_file": "services\\crypton-demo\\src\\App.js", "source_location": "L83", "weight": 1.0}, {"source": "services_crypton_demo_src_app_js", "target": "app_pageloadskeleton", "relation": "contains", "confidence": "EXTRACTED", "source_file": "services\\crypton-demo\\src\\App.js", "source_location": "L114", "weight": 1.0}, {"source": "services_crypton_demo_src_app_js", "target": "app_app", "relation": "contains", "confidence": "EXTRACTED", "source_file": "services\\crypton-demo\\src\\App.js", "source_location": "L145", "weight": 1.0}, {"source": "app_app", "target": "app_canrenderlocalauthui", "relation": "calls", "confidence": "EXTRACTED", "source_file": "services\\crypton-demo\\src\\App.js", "source_location": "L333", "weight": 1.0}], "raw_calls": [{"caller_nid": "app_canrenderlocalauthui", "callee": "has", "source_file": "services\\crypton-demo\\src\\App.js", "source_location": "L47"}, {"caller_nid": "app_redirecttoauthui", "callee": "replace", "source_file": "services\\crypton-demo\\src\\App.js", "source_location": "L58"}, {"caller_nid": "app_toaststack", "callee": "map", "source_file": "services\\crypton-demo\\src\\App.js", "source_location": "L86"}, {"caller_nid": "app_pageloadskeleton", "callee": "sk", "source_file": "services\\crypton-demo\\src\\App.js", "source_location": "L128"}, {"caller_nid": "app_pageloadskeleton", "callee": "map", "source_file": "services\\crypton-demo\\src\\App.js", "source_location": "L129"}, {"caller_nid": "app_pageloadskeleton", "callee": "sk", "source_file": "services\\crypton-demo\\src\\App.js", "source_location": "L130"}, {"caller_nid": "app_pageloadskeleton", "callee": "map", "source_file": "services\\crypton-demo\\src\\App.js", "source_location": "L131"}, {"caller_nid": "app_pageloadskeleton", "callee": "sk", "source_file": "services\\crypton-demo\\src\\App.js", "source_location": "L134"}, {"caller_nid": "app_pageloadskeleton", "callee": "sk", "source_file": "services\\crypton-demo\\src\\App.js", "source_location": "L135"}, {"caller_nid": "app_pageloadskeleton", "callee": "map", "source_file": "services\\crypton-demo\\src\\App.js", "source_location": "L137"}, {"caller_nid": "app_pageloadskeleton", "callee": "sk", "source_file": "services\\crypton-demo\\src\\App.js", "source_location": "L139"}, {"caller_nid": "app_app", "callee": "useState", "source_file": "services\\crypton-demo\\src\\App.js", "source_location": "L146"}, {"caller_nid": "app_app", "callee": "useToasts", "source_file": "services\\crypton-demo\\src\\App.js", "source_location": "L147"}, {"caller_nid": "app_app", "callee": "useRef", "source_file": "services\\crypton-demo\\src\\App.js", "source_location": "L148"}, {"caller_nid": "app_app", "callee": "getItem", "source_file": "services\\crypton-demo\\src\\App.js", "source_location": "L148"}, {"caller_nid": "app_app", "callee": "useState", "source_file": "services\\crypton-demo\\src\\App.js", "source_location": "L149"}, {"caller_nid": "app_app", "callee": "useState", "source_file": "services\\crypton-demo\\src\\App.js", "source_location": "L150"}, {"caller_nid": "app_app", "callee": "useState", "source_file": "services\\crypton-demo\\src\\App.js", "source_location": "L152"}, {"caller_nid": "app_app", "callee": "useState", "source_file": "services\\crypton-demo\\src\\App.js", "source_location": "L157"}, {"caller_nid": "app_app", "callee": "useState", "source_file": "services\\crypton-demo\\src\\App.js", "source_location": "L162"}, {"caller_nid": "app_app", "callee": "useCallback", "source_file": "services\\crypton-demo\\src\\App.js", "source_location": "L164"}, {"caller_nid": "app_app", "callee": "useEffect", "source_file": "services\\crypton-demo\\src\\App.js", "source_location": "L205"}, {"caller_nid": "app_app", "callee": "useEffect", "source_file": "services\\crypton-demo\\src\\App.js", "source_location": "L258"}, {"caller_nid": "app_app", "callee": "useCallback", "source_file": "services\\crypton-demo\\src\\App.js", "source_location": "L296"}, {"caller_nid": "app_app", "callee": "useCallback", "source_file": "services\\crypton-demo\\src\\App.js", "source_location": "L298"}, {"caller_nid": "app_app", "callee": "useCallback", "source_file": "services\\crypton-demo\\src\\App.js", "source_location": "L304"}, {"caller_nid": "app_app", "callee": "useCallback", "source_file": "services\\crypton-demo\\src\\App.js", "source_location": "L311"}, {"caller_nid": "app_app", "callee": "has", "source_file": "services\\crypton-demo\\src\\App.js", "source_location": "L326"}, {"caller_nid": "app_app", "callee": "useMemo", "source_file": "services\\crypton-demo\\src\\App.js", "source_location": "L327"}, {"caller_nid": "app_app", "callee": "has", "source_file": "services\\crypton-demo\\src\\App.js", "source_location": "L361"}, {"caller_nid": "app_app", "callee": "has", "source_file": "services\\crypton-demo\\src\\App.js", "source_location": "L361"}]}